[
  [
    "#url",
    "#title",
    "#options",
    "#tag"
  ],
  [
    "",
    "2/14 不得宣傳罷免黑客松共筆區",
    "",
    ""
  ],
  [
    "https://g0v.hackpad.com/g0v-hackath12n--cWp3e4kAJ77",
    "2/14 活動資訊",
    "",
    "行前準備:warning"
  ],
  [
    "https://kiwiirc.com/client/irc.freenode.net/#g0v.tw",
    "IRC聊天室",
    "",
    "社群溝通"
  ],
  [
    "https://g0v.hackpad.com/2mprMIpYMz9",
    "與會守則",
    "",
    "行前請讀"
  ],
  [
    "http://zbryikt.github.io/quick-timer/",
    "簡報計時器",
    "",
    ""
  ],
  [
    "",
    "提案流程",
    "",
    ""
  ],
  [
    " https://g0v.hackpad.com/g0v--JWIizPuN3mz",
    "g0v提案流程參考",
    "",
    ""
  ],
  [
    "",
    "",
    "",
    ""
  ],
  [
    " https://docs.google.com/spreadsheets/d/1dnBiLCAQwNr3uShvcITL6I8Pn00sJu3mJH0uVSO3oaM/edit#gid=1",
    "專案報告登記",
    "",
    "當天提案:important"
  ],
  [
    "",
    "",
    "",
    ""
  ],
  [
    "",
    "黑客松初心者",
    "{\"expand\":true}",
    ""
  ],
  [
    " https://g0v.hackpad.com/FAQ-gLNXqwv6krA",
    "黑客松FAQ",
    "",
    ""
  ],
  [
    " http://ipa.logdown.com/posts/166655-g0v-hackathon-nongeek",
    "非資訊人參與指南",
    "{\"target\":\"_blank\"}",
    ""
  ],
  [
    " http://ipa.logdown.com/posts/143277-g0v-proposal-tips",
    "非資訊人提案小訣竅",
    "{\"target\":\"_blank\"}",
    ""
  ],
  [
    "",
    "",
    "",
    ""
  ],
  [
    "",
    "",
    "",
    ""
  ],
  [
    "",
    "空白模版",
    "{\"expand\":false}",
    ""
  ],
  [
    " https://g0v.hackpad.com/Project-Readme-aCZGg48I5pX",
    "專案介紹空白模版",
    "",
    "常用:important"
  ],
  [
    " https://g0v.hackpad.com/Product-Planning-T2d2kAradat",
    "產品規劃空白模版",
    "",
    ""
  ],
  [
    " https://g0v.hackpad.com/User-Story-Socialtext-Style-mvxkbtlXlDf",
    "user story 空白模版",
    "",
    ""
  ],
  [
    " https://g0v.hackpad.com/dwimzocKjEL",
    "免責聲明模版",
    "",
    ""
  ],
  [
    "",
    "",
    "",
    ""
  ],
  [
    "",
    "資料",
    "{\"expand\":false}",
    ""
  ],
  [
    " http://data.gov.tw",
    "data.gov.tw",
    "",
    ""
  ],
  [
    " http://data.g0v.tw",
    "data.g0v.tw",
    "",
    ""
  ],
  [
    "",
    "",
    "",
    ""
  ],
  [
    "",
    "專案 hackpad 請加到這裡",
    "{\"expand\":true}",
    "較完整專案:important"
  ],
  [
    " https://g0v.hackpad.com/jAFuERTpDC5",
    "協助年輕人至宜蘭的平台",
    "",
    ""
  ],
  [
    " http://hackfoldr.org/Taipei-Urban-Agri/",
    "都市農耕網",
    "",
    ""
  ]
]